api2db/__init__.py
api2db/app/__init__.py
api2db/app/api2db.py
api2db/app/auth_manager.py
api2db/app/log.py
api2db/app/run.py
api2db/ingest/__init__.py
api2db/ingest/api2pandas.py
api2db/ingest/api_form.py
api2db/ingest/base_lam.py
api2db/ingest/collector.py
api2db/ingest/data_feature/__init__.py
api2db/ingest/data_feature/feature.py
api2db/ingest/post_process/__init__.py
api2db/ingest/post_process/column_add.py
api2db/ingest/post_process/column_apply.py
api2db/ingest/post_process/columns_calculate.py
api2db/ingest/post_process/date_cast.py
api2db/ingest/post_process/drop_na.py
api2db/ingest/post_process/merge_static.py
api2db/ingest/post_process/post.py
api2db/ingest/pre_process/__init__.py
api2db/ingest/pre_process/bad_row_swap.py
api2db/ingest/pre_process/feature_flatten.py
api2db/ingest/pre_process/global_extract.py
api2db/ingest/pre_process/list_extract.py
api2db/ingest/pre_process/pre.py
api2db/install/__init__.py
api2db/install/clear_lab.py
api2db/install/collector_add.py
api2db/install/collector_list.py
api2db/install/collector_remove.py
api2db/install/make_lab.py
api2db/install/project_clear.py
api2db/install/project_make.py
api2db/install/run_lab.py
api2db/store/__init__.py
api2db/store/store.py
api2db/store/store2bigquery.py
api2db/store/store2omnisci.py
api2db/store/store2sql.py
api2db/stream/__init__.py
api2db/stream/file_converter.py
api2db/stream/stream.py
api2db/stream/stream2bigquery.py
api2db/stream/stream2local.py
api2db/stream/stream2omnisci.py
api2db/stream/stream2sql.py
api2db-1.0.1.dist-info/LICENSE.txt
api2db-1.0.1.dist-info/METADATA
api2db-1.0.1.dist-info/WHEEL
api2db-1.0.1.dist-info/entry_points.txt
api2db-1.0.1.dist-info/top_level.txt
api2db-1.0.1.dist-info/RECORD
